showscore/__init__.py
showscore/html_renderer.py
showscore/music21_converter.py
showscore/opensheetmusicdisplay.min.js
showscore/show.py
showscore/showscore.js
showscore/utils.py
showscore-0.1.4.dist-info/METADATA
showscore-0.1.4.dist-info/WHEEL
showscore-0.1.4.dist-info/top_level.txt
showscore-0.1.4.dist-info/RECORD
