Metadata-Version: 2.1
Name: showscore
Version: 0.1.4
Summary: Render music21 scores in jupyter notebooks
Author: Sven Hollowell
License: MIT
Project-URL: Homepage, https://github.com/supersational/showscore
Project-URL: Changelog, https://github.com/supersational/showscore/releases
Project-URL: Issues, https://github.com/supersational/showscore/issues
Requires-Python: >=3.8
Requires-Dist: music21
